pvnet/__init__.py
pvnet/datamodule.py
pvnet/load_model.py
pvnet/optimizers.py
pvnet/utils.py
pvnet/models/__init__.py
pvnet/models/base_model.py
pvnet/models/ensemble.py
pvnet/models/late_fusion/__init__.py
pvnet/models/late_fusion/basic_blocks.py
pvnet/models/late_fusion/late_fusion.py
pvnet/models/late_fusion/encoders/__init__.py
pvnet/models/late_fusion/encoders/basic_blocks.py
pvnet/models/late_fusion/encoders/encoders3d.py
pvnet/models/late_fusion/linear_networks/__init__.py
pvnet/models/late_fusion/linear_networks/basic_blocks.py
pvnet/models/late_fusion/linear_networks/networks.py
pvnet/models/late_fusion/site_encoders/__init__.py
pvnet/models/late_fusion/site_encoders/basic_blocks.py
pvnet/models/late_fusion/site_encoders/encoders.py
pvnet/training/__init__.py
pvnet/training/lightning_module.py
pvnet/training/plots.py
pvnet/training/train.py
pvnet-5.3.8.dist-info/licenses/LICENSE
pvnet-5.3.8.dist-info/METADATA
pvnet-5.3.8.dist-info/WHEEL
pvnet-5.3.8.dist-info/top_level.txt
pvnet-5.3.8.dist-info/RECORD
