Metadata-Version: 2.4
Name: PVNet
Version: 5.3.8
Summary: PVNet
Author-email: Peter Dudfield <info@openclimatefix.org>
Requires-Python: <3.14,>=3.11
License-File: LICENSE
Requires-Dist: ocf-data-sampler>=1.0.9
Requires-Dist: numpy
Requires-Dist: pandas
Requires-Dist: matplotlib
Requires-Dist: xarray
Requires-Dist: h5netcdf
Requires-Dist: torch>=2.0.0
Requires-Dist: lightning
Requires-Dist: typer
Requires-Dist: sqlalchemy
Requires-Dist: fsspec[s3]
Requires-Dist: wandb
Requires-Dist: huggingface-hub
Requires-Dist: tqdm
Requires-Dist: omegaconf
Requires-Dist: hydra-core
Requires-Dist: rich
Requires-Dist: einops
Requires-Dist: safetensors
Dynamic: license-file
